votakvot/__init__.py
votakvot/absolutely.py
votakvot/core.py
votakvot/data.py
votakvot/hook.py
votakvot/meta.py
votakvot/metrics.py
votakvot/report.py
votakvot/resumable.py
votakvot/runner.py
votakvot/extras/__init__.py
votakvot/extras/beam.py
votakvot/extras/beam_plugin.py
votakvot/extras/gcm.py
votakvot/extras/prometheus.py
votakvot-0.1.dev2.dist-info/LICENSE
votakvot-0.1.dev2.dist-info/METADATA
votakvot-0.1.dev2.dist-info/WHEEL
votakvot-0.1.dev2.dist-info/entry_points.txt
votakvot-0.1.dev2.dist-info/top_level.txt
votakvot-0.1.dev2.dist-info/RECORD
